{"_type":"export","__export_format":4,"__export_date":"2023-10-14T16:54:09.437Z","__export_source":"insomnia.desktop.app:v8.2.0","resources":[{"_id":"req_6c681a4a1b26472883d4192e1d8c0576","parentId":"fld_cc8f3ffc9da8461aab79ed1e7368dc55","modified":1697302347338,"created":1697301539085,"url":"{{ _.BASE_URL }}/users/4/property_users/1","name":"Update","description":"","method":"PATCH","body":{"mimeType":"application/json","text":"{\n\t\"favorite\": \"false\",\n\t\"contacted\": \"true\"\n}"},"parameters":[],"headers":[{"name":"Content-Type","value":"application/json"},{"id":"pair_97e5a63241834af293661efb5abd9535","name":"Authorization","value":"Token token={{token}}","description":""}],"authentication":{},"metaSortKey":-1697301539085,"isPrivate":false,"settingStoreCookies":true,"settingSendCookies":true,"settingDisableRenderRequestBody":false,"settingEncodeUrl":true,"settingRebuildPath":true,"settingFollowRedirects":"global","_type":"request"},{"_id":"fld_cc8f3ffc9da8461aab79ed1e7368dc55","parentId":"wrk_df2b1b42bfa34888b33dc1c2084906e8","modified":1697301385063,"created":1697301385063,"name":"Property User","description":"","environment":{},"environmentPropertyOrder":null,"metaSortKey":-1697301385063,"_type":"request_group"},{"_id":"wrk_df2b1b42bfa34888b33dc1c2084906e8","parentId":null,"modified":1697297041159,"created":1697297041159,"name":"First-version","description":"","scope":"collection","_type":"workspace"},{"_id":"req_c0417213c6bf4c08b8378ceed3d00b56","parentId":"fld_cc8f3ffc9da8461aab79ed1e7368dc55","modified":1697301861628,"created":1697301408749,"url":"{{ _.BASE_URL }}/users/4/property_users","name":"Index","description":"","method":"GET","body":{},"parameters":[],"headers":[{"name":"Authorization","value":"Token token={{token}}","id":"pair_91e313fda9dd481e8060f6c37f506e8e"}],"authentication":{},"metaSortKey":-1697301408749,"isPrivate":false,"settingStoreCookies":true,"settingSendCookies":true,"settingDisableRenderRequestBody":false,"settingEncodeUrl":true,"settingRebuildPath":true,"settingFollowRedirects":"global","_type":"request"},{"_id":"req_b042d44aad5541c78a4e8e6b0eb87faa","parentId":"fld_cc8f3ffc9da8461aab79ed1e7368dc55","modified":1697302216798,"created":1697301405768,"url":"{{ _.BASE_URL }}/users/4/property_users","name":"Create","description":"","method":"POST","body":{"mimeType":"application/json","text":"{\n\t\"property_id\": 10,\n\t\"favorite\": \"true\",\n\t\"contacted\": \"false\"\n}"},"parameters":[],"headers":[{"name":"Content-Type","value":"application/json","id":"pair_c29a6d1ace994681a87ee5382c177451"},{"name":"Authorization","value":"Token token={{token}}","id":"pair_3748aebf77a041569b109e635a7338f2"}],"authentication":{},"metaSortKey":-1697301405768,"isPrivate":false,"settingStoreCookies":true,"settingSendCookies":true,"settingDisableRenderRequestBody":false,"settingEncodeUrl":true,"settingRebuildPath":true,"settingFollowRedirects":"global","_type":"request"},{"_id":"req_7539f56a8b6f464f9a68e78abb0c1cbd","parentId":"fld_cc8f3ffc9da8461aab79ed1e7368dc55","modified":1697302390942,"created":1697301392032,"url":"{{ _.BASE_URL }}/users/4/property_users/1","name":"Delete","description":"","method":"DELETE","body":{},"parameters":[],"headers":[{"name":"Authorization","value":"Token token={{token}}","id":"pair_1c48e1663d3349f5b305f78fe4b0082a"}],"authentication":{},"metaSortKey":-1697301392032,"isPrivate":false,"settingStoreCookies":true,"settingSendCookies":true,"settingDisableRenderRequestBody":false,"settingEncodeUrl":true,"settingRebuildPath":true,"settingFollowRedirects":"global","_type":"request"},{"_id":"req_c31d43c9ba4d4894a163703756fc53fd","parentId":"fld_1b9ba13cd66e4bf783fe126b27f27450","modified":1697298025156,"created":1697231676773,"url":"{{ _.BASE_URL }}/user_property_rents","name":"Create Property Rent","description":"","method":"POST","body":{"mimeType":"application/json","text":"{\n\"address\": \"Av. Ayacucho 128\",\n\"bedroom\": 4,\n\"bathroom\":2,\n\"area\": 200,\n\"description\": \"terreno en plaza\",\n\"photo_url\": [\"https://res.cloudinary.com/dvxvdktvr/image/upload/v1697046792/d3h7lv5hnyq2ukk0ufyh.png\"],\n\"active\":true,\n\"monthly_rent\": 5,\n\"maintenance\": 2,\n\"pets_allowed\": false,\n\"property_type\": 1\n}"},"parameters":[],"headers":[{"name":"Authorization","value":"Token token={{ token }}","id":"pair_b8686b2bd5eb4f47bbc3bdb6ed077e12"},{"id":"pair_9cd76be0c0464f63af21bd7c437f74b2","name":"Content-Type","value":"application/json","description":""}],"authentication":{},"metaSortKey":-1697231625403,"isPrivate":false,"settingStoreCookies":true,"settingSendCookies":true,"settingDisableRenderRequestBody":false,"settingEncodeUrl":true,"settingRebuildPath":true,"settingFollowRedirects":"global","_type":"request"},{"_id":"fld_1b9ba13cd66e4bf783fe126b27f27450","parentId":"wrk_df2b1b42bfa34888b33dc1c2084906e8","modified":1697231597517,"created":1697231597517,"name":"Properties Rent","description":"","environment":{},"environmentPropertyOrder":null,"metaSortKey":-1697231597517,"_type":"request_group"},{"_id":"req_8dbf36fec4b4409db623ff33a0fa7190","parentId":"fld_1b9ba13cd66e4bf783fe126b27f27450","modified":1697231653342,"created":1697231601488,"url":"{{ _.BASE_URL }}/user_property_rents","name":"Index Properties Sale","description":"","method":"GET","body":{},"parameters":[],"headers":[{"name":"Authorization","value":"Token token={{ token }}","id":"pair_2b45e362013e4ef7ab8f5f38cb3654ce"}],"authentication":{},"metaSortKey":-1697231625303,"isPrivate":false,"settingStoreCookies":true,"settingSendCookies":true,"settingDisableRenderRequestBody":false,"settingEncodeUrl":true,"settingRebuildPath":true,"settingFollowRedirects":"global","_type":"request"},{"_id":"req_62b3a6c79e764ce7be6801b9ac298953","parentId":"fld_cfdff0e827404661afcd7fd8a4ba7717","modified":1697216191300,"created":1697207216951,"url":"{{ _.BASE_URL }}/user_property_sales","name":"Index Properties Sales","description":"","method":"GET","body":{},"parameters":[],"headers":[{"id":"pair_338ad05ee7f3450184e9c6f4925ed1a9","name":"Authorization","value":"Token token={{ token }}","description":""}],"authentication":{},"metaSortKey":-1697207286169,"isPrivate":false,"settingStoreCookies":true,"settingSendCookies":true,"settingDisableRenderRequestBody":false,"settingEncodeUrl":true,"settingRebuildPath":true,"settingFollowRedirects":"global","_type":"request"},{"_id":"fld_cfdff0e827404661afcd7fd8a4ba7717","parentId":"wrk_df2b1b42bfa34888b33dc1c2084906e8","modified":1697228255119,"created":1697207212369,"name":"Properties Sale","description":"","environment":{},"environmentPropertyOrder":null,"metaSortKey":-1697207212369,"_type":"request_group"},{"_id":"req_09aa422aa5da4ed19df8d0be5137bff3","parentId":"fld_cfdff0e827404661afcd7fd8a4ba7717","modified":1697239315273,"created":1697211451473,"url":"{{ _.BASE_URL }}/user_property_sales","name":"Create Property Sale","description":"","method":"POST","body":{"mimeType":"application/json","text":"{\n\"address\": \"Av. Cusco 128\",\n\"bedroom\": 4,\n\"bathroom\":2,\n\"area\": 200,\n\"description\": \"terreno en plaza\",\n\"photo_url\": [\"https://res.cloudinary.com/dvxvdktvr/image/upload/v1697046792/d3h7lv5hnyq2ukk0ufyh.png\"],\n\"price\": 1200,\n\"active\":true,\n\"property_type\": 1\n}"},"parameters":[],"headers":[{"name":"Authorization","value":"Token token={{ token }}","id":"pair_b8686b2bd5eb4f47bbc3bdb6ed077e12"},{"id":"pair_9cd76be0c0464f63af21bd7c437f74b2","name":"Content-Type","value":"application/json","description":""}],"authentication":{},"metaSortKey":-1697207286069,"isPrivate":false,"settingStoreCookies":true,"settingSendCookies":true,"settingDisableRenderRequestBody":false,"settingEncodeUrl":true,"settingRebuildPath":true,"settingFollowRedirects":"global","_type":"request"},{"_id":"req_44081b8964224f7ca0286c63351c519c","parentId":"fld_b7b40b3f3b014c8b9707e252dbb4538c","modified":1697296305778,"created":1697144251484,"url":"{{ _.BASE_URL }}/login","name":"login","description":"","method":"POST","body":{"mimeType":"application/json","text":"{\n\t\"email\": \"cverah_home@mail.com\",\n\t\"password\": \"123456\"\n}"},"parameters":[],"headers":[{"name":"Content-Type","value":"application/json","id":"pair_42b093cc90834785b200f6fb871213ca"}],"authentication":{},"metaSortKey":-1697144253790,"isPrivate":false,"settingStoreCookies":true,"settingSendCookies":true,"settingDisableRenderRequestBody":false,"settingEncodeUrl":true,"settingRebuildPath":true,"settingFollowRedirects":"global","_type":"request"},{"_id":"fld_b7b40b3f3b014c8b9707e252dbb4538c","parentId":"wrk_df2b1b42bfa34888b33dc1c2084906e8","modified":1697130873381,"created":1697130873381,"name":"Session","description":"","environment":{},"environmentPropertyOrder":null,"metaSortKey":-1697130873381,"_type":"request_group"},{"_id":"req_89e9f9fcafd54b2db8e8beb66d48994e","parentId":"fld_b7b40b3f3b014c8b9707e252dbb4538c","modified":1697146079039,"created":1697145162961,"url":"{{ _.BASE_URL }}/logout","name":"logout","description":"","method":"DELETE","body":{},"parameters":[],"headers":[{"name":"Authorization","value":"Token token={{ token }}","id":"pair_5eb87adea9f54fa9b13c080512d91dc4","disabled":false}],"authentication":{},"metaSortKey":-1697144253690,"isPrivate":false,"settingStoreCookies":true,"settingSendCookies":true,"settingDisableRenderRequestBody":false,"settingEncodeUrl":true,"settingRebuildPath":true,"settingFollowRedirects":"global","_type":"request"},{"_id":"req_0cd58b5ea8414987af692fa2d7b0dfff","parentId":"fld_a3cd1f9094b745a48bbc0177cfb32e1c","modified":1697232257387,"created":1697232126025,"url":"{{ _.BASE_URL }}/profile","name":"Update Users","description":"","method":"PATCH","body":{"mimeType":"application/json","text":"{\n\t\"name\": \"newUser\",\n\t\"password\": \"1234567\",\n\t\"phone\":\"928646027\",\n\t\"role\": 1\n\n}"},"parameters":[],"headers":[{"name":"Content-Type","value":"application/json","id":"pair_e091729cd32c4f7b95f66183accfffbe"},{"name":"Authorization","value":"Token token={{ token }}","id":"pair_52f454c4853642f2b263d3c0d459a791"}],"authentication":{},"metaSortKey":-1697130911058,"isPrivate":false,"settingStoreCookies":true,"settingSendCookies":true,"settingDisableRenderRequestBody":false,"settingEncodeUrl":true,"settingRebuildPath":true,"settingFollowRedirects":"global","_type":"request"},{"_id":"fld_a3cd1f9094b745a48bbc0177cfb32e1c","parentId":"wrk_df2b1b42bfa34888b33dc1c2084906e8","modified":1697130862338,"created":1697130862338,"name":"User","description":"","environment":{},"environmentPropertyOrder":null,"metaSortKey":-1697130862338,"_type":"request_group"},{"_id":"req_06cf3305d09c40c8935720106c4a1f0a","parentId":"fld_a3cd1f9094b745a48bbc0177cfb32e1c","modified":1697230656480,"created":1697228276692,"url":"{{ _.BASE_URL }}/show_properties","name":"Show Properties","description":"","method":"GET","body":{},"parameters":[],"headers":[{"id":"pair_618c510c7fbd48b480e8376f48faede7","name":"Authorization","value":"Token token={{ token }}","description":""}],"authentication":{},"metaSortKey":-1697130910958,"isPrivate":false,"settingStoreCookies":true,"settingSendCookies":true,"settingDisableRenderRequestBody":false,"settingEncodeUrl":true,"settingRebuildPath":true,"settingFollowRedirects":"global","_type":"request"},{"_id":"req_75a0187b2ae34f0c935ca3ebe9e736fe","parentId":"fld_a3cd1f9094b745a48bbc0177cfb32e1c","modified":1697163337809,"created":1697162693334,"url":"{{ _.BASE_URL }}/profile","name":"Profile User","description":"","method":"GET","body":{},"parameters":[],"headers":[{"name":"Authorization","value":"Token token={{ token }}","id":"pair_798eef244312409ebf286c68fb8f4241"}],"authentication":{},"metaSortKey":-1697130910858,"isPrivate":false,"settingStoreCookies":true,"settingSendCookies":true,"settingDisableRenderRequestBody":false,"settingEncodeUrl":true,"settingRebuildPath":true,"settingFollowRedirects":"global","_type":"request"},{"_id":"req_e60dec733c2b4e9eb8f9f66c8cde522a","parentId":"fld_a3cd1f9094b745a48bbc0177cfb32e1c","modified":1697295636352,"created":1697130898018,"url":"{{ _.BASE_URL }}/signup","name":"Create Users","description":"","method":"POST","body":{"mimeType":"application/json","text":"{\n\t\"name\": \"newUser\",\n\t\"email\": \"newussesr@mail.com\",\n\t\"password\": \"123456\",\n\t\"phone\":\"928646027\",\n\t\"role\": 1\n\n}"},"parameters":[],"headers":[{"name":"Content-Type","value":"application/json","id":"pair_46f5f0d373d84af68d76541d4c0a2a90"}],"authentication":{},"metaSortKey":-1697130910758,"isPrivate":false,"settingStoreCookies":true,"settingSendCookies":true,"settingDisableRenderRequestBody":false,"settingEncodeUrl":true,"settingRebuildPath":true,"settingFollowRedirects":"global","_type":"request"},{"_id":"req_a142317e6796495ebdbebdaba54cade8","parentId":"fld_47b29e8aa8ef493893f0b1cbad3a4eef","modified":1697296229161,"created":1697296138307,"url":"{{ _.BASE_URL }}/properties/3","name":"Delete Property","description":"","method":"DELETE","body":{},"parameters":[],"headers":[{"id":"pair_62bc020e46eb48b29178a337fbb3bc1a","name":"Authorization","value":"Token token={{ token }}","description":""}],"authentication":{},"metaSortKey":-1697043286180,"isPrivate":false,"settingStoreCookies":true,"settingSendCookies":true,"settingDisableRenderRequestBody":false,"settingEncodeUrl":true,"settingRebuildPath":true,"settingFollowRedirects":"global","_type":"request"},{"_id":"fld_47b29e8aa8ef493893f0b1cbad3a4eef","parentId":"wrk_df2b1b42bfa34888b33dc1c2084906e8","modified":1697043267200,"created":1697043267200,"name":"Properties","description":"","environment":{},"environmentPropertyOrder":null,"metaSortKey":-1697043267200,"_type":"request_group"},{"_id":"req_65718655677444a2b0879182a1bfc57f","parentId":"fld_47b29e8aa8ef493893f0b1cbad3a4eef","modified":1697296044857,"created":1697242744993,"url":"{{ _.BASE_URL }}/users/2/properties/3","name":"Update Properties","description":"","method":"PATCH","body":{"mimeType":"application/json","text":"{\n      \n        \"operation_type\": \"rent\",\n        \"address\": \"Av. Jesus Maria \",\n        \"property_type\": \"apartment\",\n        \"bedrooms\": 0,\n        \"bathrooms\": 0,\n        \"area\": 0,\n        \"description\": \"bonito depa\",\n        \"photo_url\": [\"https://res.cloudinary.com/dvxvdktvr/image/upload/v1697046792/d3h7lv5hnyq2ukk0ufyh.png\"],\n        \"active\": true,\n        \"price\": 0,\n        \"monthly_rent\": 0,\n        \"maintenance\": 0,\n        \"pets_allowed\": false,\n        \"latitud\": \"\",\n        \"longitud\": \"\"\n    }"},"parameters":[],"headers":[{"name":"Content-Type","value":"application/json","id":"pair_e6885181770b435b99febb763efb98ce"},{"name":"Authorization","value":"Token token={{ token }}","id":"pair_83cec713ea5f4a4ebe3df801ebc92592"}],"authentication":{},"metaSortKey":-1697043286080,"isPrivate":false,"settingStoreCookies":true,"settingSendCookies":true,"settingDisableRenderRequestBody":false,"settingEncodeUrl":true,"settingRebuildPath":true,"settingFollowRedirects":"global","_type":"request"},{"_id":"req_0f71824bdb3549c39661ab034968869e","parentId":"fld_47b29e8aa8ef493893f0b1cbad3a4eef","modified":1697295835716,"created":1697242662772,"url":"{{ _.BASE_URL }}/users/2/properties/3","name":"Show Properties","description":"","method":"GET","body":{},"parameters":[],"headers":[],"authentication":{},"metaSortKey":-1697043285980,"isPrivate":false,"settingStoreCookies":true,"settingSendCookies":true,"settingDisableRenderRequestBody":false,"settingEncodeUrl":true,"settingRebuildPath":true,"settingFollowRedirects":"global","_type":"request"},{"_id":"req_c4a6283e00944eec9a8b3cde9db196ab","parentId":"fld_47b29e8aa8ef493893f0b1cbad3a4eef","modified":1697061843023,"created":1697043282987,"url":"{{ _.BASE_URL }}/properties","name":"Index Properties","description":"","method":"GET","body":{},"parameters":[],"headers":[],"authentication":{},"metaSortKey":-1697043285880,"isPrivate":false,"settingStoreCookies":true,"settingSendCookies":true,"settingDisableRenderRequestBody":false,"settingEncodeUrl":true,"settingRebuildPath":true,"settingFollowRedirects":"global","_type":"request"},{"_id":"env_328323c91409f8a0a2d18b6d0849080021e63335","parentId":"wrk_df2b1b42bfa34888b33dc1c2084906e8","modified":1697298001762,"created":1697297041169,"name":"Base Environment","data":{"base_url":"localhost:300/","token":""},"dataPropertyOrder":{"&":["base_url","token"]},"color":null,"isPrivate":false,"metaSortKey":1697297041170,"_type":"environment"},{"_id":"jar_328323c91409f8a0a2d18b6d0849080021e63335","parentId":"wrk_df2b1b42bfa34888b33dc1c2084906e8","modified":1697297041181,"created":1697297041181,"name":"Default Jar","cookies":[],"_type":"cookie_jar"},{"_id":"env_60ffa59f671b4c04afad9d2e107ee3c1","parentId":"env_328323c91409f8a0a2d18b6d0849080021e63335","modified":1697301767235,"created":1697044494659,"name":"localhost","data":{"BASE_URL":"http://localhost:3000","token":"t9Jev2U9PKLwgozqR7r5PujK"},"dataPropertyOrder":{"&":["BASE_URL","token"]},"color":"#7d69cb","isPrivate":false,"metaSortKey":1697044494659,"_type":"environment"}]}